LICENSE
README.md
pyproject.toml
setup.cfg
setup.py
pynq_compute_labs/__init__.py
pynq_compute_labs.egg-info/PKG-INFO
pynq_compute_labs.egg-info/SOURCES.txt
pynq_compute_labs.egg-info/dependency_links.txt
pynq_compute_labs.egg-info/entry_points.txt
pynq_compute_labs.egg-info/requires.txt
pynq_compute_labs.egg-info/top_level.txt
pynq_compute_labs/notebooks/introduction/Introduction.ipynb
pynq_compute_labs/notebooks/introduction/Jupyter.ipynb
pynq_compute_labs/notebooks/introduction/Resources.ipynb
pynq_compute_labs/notebooks/introduction/__init__.py
pynq_compute_labs/notebooks/introduction/img/command_mode.png
pynq_compute_labs/notebooks/introduction/img/edit_mode.png
pynq_compute_labs/notebooks/introduction/img/file_browser.png
pynq_compute_labs/notebooks/introduction/img/launcher.png
pynq_compute_labs/notebooks/introduction/img/running_kernels.png
pynq_compute_labs/notebooks/introduction/img/toolbar.png
pynq_compute_labs/notebooks/introduction/img/windows.png
pynq_compute_labs/notebooks/labs/1-vadd.ipynb
pynq_compute_labs/notebooks/labs/2-optimization.ipynb
pynq_compute_labs/notebooks/labs/3-compression.ipynb
pynq_compute_labs/notebooks/labs/compression.xclbin.link
pynq_compute_labs/notebooks/labs/intro.xclbin.link
pynq_compute_labs/notebooks/labs/test_data.bin.link
pynq_compute_labs/notebooks/labs/img/lzx_comp.png
pynq_compute_labs/notebooks/labs/img/vadd_2_no_overlap.svg
pynq_compute_labs/notebooks/labs/img/vadd_2_overlap.svg
pynq_compute_labs/notebooks/labs/img/vadd_highlight.svg
pynq_compute_labs/notebooks/labs/img/vadd_single.svg
pynq_compute_labs/notebooks/labs/img/vmac_no_overlap.svg
pynq_compute_labs/notebooks/labs/img/vmac_overlap.svg