Metadata-Version: 2.1
Name: pynq-compute-labs
Version: 0.3.0
Summary: Package for the PYNQ Compute Acceleration Labs
Author: Peter Ogden
Author-email: pynq_support@xilinx.com
License: Apache License 2.0
Classifier: License :: OSI Approved :: Apache Software License
Requires-Python: >=3.8.0
License-File: LICENSE
